pydml/__init__.py
pydml/analysis/__init__.py
pydml/analysis/loss_landscape.py
pydml/analysis/robustness.py
pydml/analysis/visualization.py
pydml/core/__init__.py
pydml/core/base_trainer.py
pydml/core/callbacks.py
pydml/core/losses.py
pydml/losses/__init__.py
pydml/losses/attention_transfer.py
pydml/models/__init__.py
pydml/models/cifar/__init__.py
pydml/models/cifar/mobilenet.py
pydml/models/cifar/resnet.py
pydml/models/cifar/vgg.py
pydml/models/cifar/wrn.py
pydml/strategies/__init__.py
pydml/strategies/curriculum.py
pydml/strategies/peer_selection.py
pydml/strategies/temperature_scaling.py
pydml/trainers/__init__.py
pydml/trainers/co_distillation.py
pydml/trainers/confidence_weighted.py
pydml/trainers/distillation.py
pydml/trainers/dml.py
pydml/trainers/feature_dml.py
pydml/utils/__init__.py
pydml/utils/amp.py
pydml/utils/data.py
pydml/utils/distributed.py
pydml/utils/ensemble.py
pydml/utils/export.py
pydml/utils/hyperparameter_search.py
pydml/utils/logging.py
pydml/utils/metrics.py
pydml/utils/schedulers.py
pytorch_dml-1.1.0.dist-info/licenses/LICENSE
pytorch_dml-1.1.0.dist-info/METADATA
pytorch_dml-1.1.0.dist-info/WHEEL
pytorch_dml-1.1.0.dist-info/top_level.txt
pytorch_dml-1.1.0.dist-info/RECORD
