Metadata-Version: 2.4
Name: pytorch-dml
Version: 1.1.0
Summary: A production-ready library for Deep Mutual Learning and collaborative neural network training
Home-page: https://github.com/VARUN3WARE/dml-py
Author: Varun Rao
Author-email: varunrao.gd@gmail.com
Project-URL: Bug Tracker, https://github.com/VARUN3WARE/dml-py/issues
Project-URL: Documentation, https://github.com/VARUN3WARE/dml-py/blob/main/README.md
Project-URL: Source Code, https://github.com/VARUN3WARE/dml-py
Keywords: deep-learning mutual-learning knowledge-distillation pytorch collaborative-learning neural-networks
Classifier: Development Status :: 4 - Beta
Classifier: Intended Audience :: Developers
Classifier: Intended Audience :: Science/Research
Classifier: Intended Audience :: Education
Classifier: Topic :: Scientific/Engineering :: Artificial Intelligence
Classifier: Topic :: Scientific/Engineering :: Image Recognition
Classifier: License :: OSI Approved :: MIT License
Classifier: Programming Language :: Python :: 3
Classifier: Programming Language :: Python :: 3.8
Classifier: Programming Language :: Python :: 3.9
Classifier: Programming Language :: Python :: 3.10
Classifier: Programming Language :: Python :: 3.11
Classifier: Programming Language :: Python :: 3.12
Classifier: Operating System :: OS Independent
Requires-Python: >=3.8
License-File: LICENSE
Requires-Dist: torch>=2.0.0
Requires-Dist: torchvision>=0.15.0
Requires-Dist: numpy>=1.21.0
Requires-Dist: tqdm>=4.65.0
Requires-Dist: tensorboard>=2.13.0
Requires-Dist: matplotlib>=3.5.0
Provides-Extra: dev
Requires-Dist: pytest>=7.3.0; extra == "dev"
Requires-Dist: pytest-cov>=4.1.0; extra == "dev"
Requires-Dist: black>=23.3.0; extra == "dev"
Requires-Dist: flake8>=6.0.0; extra == "dev"
Requires-Dist: isort>=5.12.0; extra == "dev"
Requires-Dist: mypy>=1.3.0; extra == "dev"
Requires-Dist: sphinx>=6.2.0; extra == "dev"
Requires-Dist: sphinx-rtd-theme>=1.2.0; extra == "dev"
Provides-Extra: optuna
Requires-Dist: optuna>=3.0.0; extra == "optuna"
Provides-Extra: onnx
Requires-Dist: onnx>=1.14.0; extra == "onnx"
Requires-Dist: onnxruntime>=1.15.0; extra == "onnx"
Provides-Extra: all
Requires-Dist: optuna>=3.0.0; extra == "all"
Requires-Dist: onnx>=1.14.0; extra == "all"
Requires-Dist: onnxruntime>=1.15.0; extra == "all"
Requires-Dist: jupyter>=1.0.0; extra == "all"
Requires-Dist: seaborn>=0.12.0; extra == "all"
Dynamic: author
Dynamic: author-email
Dynamic: classifier
Dynamic: description
Dynamic: description-content-type
Dynamic: home-page
Dynamic: keywords
Dynamic: license-file
Dynamic: project-url
Dynamic: provides-extra
Dynamic: requires-dist
Dynamic: requires-python
Dynamic: summary
